{
    "achievement.floor_3.name": "Beat Floor 3",
    "achievement.floor_3.description": "The beginning of the descent.",
    "achievement.floor_2.name": "Beat Floor 2",
    "achievement.floor_2.description": "Reach the halfway point.",
    "achievement.floor_1.name": "Beat Floor 1",
    "achievement.floor_1.description": "The final challenge awaits.",
    "achievement.complete_run.name": "Complete A Run",
    "achievement.complete_run.description": "Complete a full run through all floors.",
    "achievement.all_cardpacks.name": "Pack Collector",
    "achievement.all_cardpacks.description": "Find all available card packs.",
    "achievement.all_cards.name": "Card Collector",
    "achievement.all_cards.description": "Find all available cards.",
    "achievement.all_relics.name": "Relic Collector",
    "achievement.all_relics.description": "Find all available relics.",
    "achievement.collector.name": "True Collector",
    "achievement.collector.description": "Complete the collection.",
    "achievement.die_tutorial.name": "Lesson Unlearned",
    "achievement.die_tutorial.description": "Die in the tutorial.",
    "achievement.all_enemies.name": "Hunter",
    "achievement.all_enemies.description": "Complete the bestiary."
}